{"status": "ok", "articles": [{"description": "\u00ce\u009d\u00ce\u00ad\u00ce\u00b1, \u00ce\u009f\u00ce\u00bc\u00ce\u00ac\u00ce\u00b4\u00ce\u00b5\u00cf\u0082, \u00ce\u00a0\u00cf\u0081\u00cf\u008c\u00ce\u00b3\u00cf\u0081\u00ce\u00b1\u00ce\u00bc\u00ce\u00bc\u00ce\u00b1, \u00ce\u0091\u00cf\u0080\u00ce\u00bf\u00cf\u0084\u00ce\u00b5\u00ce\u00bb\u00ce\u00ad\u00cf\u0083\u00ce\u00bc\u00ce\u00b1\u00cf\u0084\u00ce\u00b1, \u00ce\u0092\u00ce\u00b1\u00ce\u00b8\u00ce\u00bc\u00ce\u00bf\u00ce\u00bb\u00ce\u00bf\u00ce\u00b3\u00ce\u00af\u00ce\u00b5\u00cf\u0082, \u00ce\u00a3\u00cf\u0084\u00ce\u00b1\u00cf\u0084\u00ce\u00b9\u00cf\u0083\u00cf\u0084\u00ce\u00b9\u00ce\u00ba\u00ce\u00ac - SPORT 24", "title": "\u039b\u03ad\u03c3\u03c4\u03b5\u03c1 - \u0391\u0395\u039a 2-0: \u03a4\u03b7\u03bd \u03ba\u03b1\u03b8\u03ac\u03c1\u03b9\u03c3\u03b5 \u03bc\u03ad\u03c3\u03b1 \u03c3\u03b5 \u03b4\u03cd\u03bf \u03bb\u03b5\u03c0\u03c4\u03ac - SPORT24", "url": "https://www.sport24.gr/football/lester-aek-europa-league-video.9077237.html", "author": "\u00ce\u009a\u00cf\u008e\u00cf\u0083\u00cf\u0084\u00ce\u00b1\u00cf\u0082 \u00ce\u0091\u00cf\u0085\u00ce\u00b3\u00ce\u00bf\u00cf\u0085\u00cf\u0083\u00cf\u0084\u00ce\u00ac\u00ce\u00ba\u00ce\u00b7\u00cf\u0082", "publishedAt": "2020-12-10T21:55:00Z", "content": "\u00ce\u00a4\u00ce\u00b7\u00ce\u00bd \u00cf\u0080\u00ce\u00ad\u00ce\u00bc\u00cf\u0080\u00cf\u0084\u00ce\u00b7 \u00cf\u0084\u00ce\u00b7\u00cf\u0082 \u00ce\u00ae\u00cf\u0084\u00cf\u0084\u00ce\u00b1 \u00cf\u0083\u00cf\u0084\u00ce\u00b7 \u00cf\u0086\u00ce\u00ac\u00cf\u0083\u00ce\u00b7 \u00cf\u0084\u00cf\u0089\u00ce\u00bd \u00ce\u00bf\u00ce\u00bc\u00ce\u00af\u00ce\u00bb\u00cf\u0089\u00ce\u00bd \u00cf\u0084\u00ce\u00bf\u00cf\u0085 Europa League \u00ce\u00b4\u00ce\u00ad\u00cf\u0087\u00ce\u00b8\u00ce\u00b7\u00ce\u00ba\u00ce\u00b5 \u00ce\u00b7 \u00ce\u0091\u00ce\u0095\u00ce\u009a. \u00ce\u0097 \u00ce\u0088\u00ce\u00bd\u00cf\u0089\u00cf\u0083\u00ce\u00b7 \u00ce\u00b4\u00ce\u00b5\u00ce\u00bd \u00ce\u00bc\u00cf\u0080\u00ce\u00bf\u00cf\u0081\u00ce\u00bf\u00cf\u008d\u00cf\u0083\u00ce\u00b5 \u00ce\u00bd\u00ce\u00b1 \u00ce\u00ba\u00ce\u00ac\u00ce\u00bd\u00ce\u00b5\u00ce\u00b9 \u00ce\u00ba\u00ce\u00ac\u00cf\u0084\u00ce\u00b9 \u00cf\u0083\u00cf\u0084\u00ce\u00bf King Power\u2026 [+6908 chars]", "source": {"id": null, "name": "Sport24.gr"}, "urlToImage": "https://www.sport24.gr/img/1276/9077279/043000/fb1200/1200/lester-aek.jpg"}, {"description": "\u039c\u03b5\u03b3\u03ac\u03bb\u03b7 \u03c0\u03bf\u03c3\u03cc\u03c4\u03b7\u03c4\u03b1 \u03bd\u03b5\u03c1\u03bf\u03cd \u03c3\u03c5\u03b3\u03ba\u03b5\u03bd\u03c4\u03c1\u03ce\u03b8\u03b7\u03ba\u03b5 \u03c3\u03b5 \u03c3\u03c5\u03b3\u03ba\u03b5\u03ba\u03c1\u03b9\u03bc\u03ad\u03bd\u03bf \u03c3\u03b7\u03bc\u03b5\u03af\u03bf \u03c4\u03bf\u03c5 \u0399\u03b5\u03c1\u03bf\u03cd \u0392\u03c1\u03ac\u03c7\u03bf\u03c5 \u03c0\u03c1\u03bf\u03ba\u03b1\u03bb\u03ce\u03bd\u03c4\u03b1\u03c2 \u03c0\u03c1\u03bf\u03b2\u03bb\u03b7\u03bc\u03b1\u03c4\u03b9\u03c3\u03bc\u03cc #CNNgrNews", "title": "\u039a\u03b1\u03ba\u03bf\u03ba\u03b1\u03b9\u03c1\u03af\u03b1: \u03a0\u03bb\u03b7\u03bc\u03bc\u03cd\u03c1\u03b9\u03c3\u03b5 \u03b7 \u0391\u03ba\u03c1\u03cc\u03c0\u03bf\u03bb\u03b7 \u03b1\u03c0\u03cc \u03c4\u03b7\u03bd \u03ba\u03b1\u03c4\u03b1\u03b9\u03b3\u03af\u03b4\u03b1 - \u03a4\u03b9 \u03b1\u03c0\u03b1\u03bd\u03c4\u03ac \u03b7 \u039c\u03b5\u03bd\u03b4\u03ce\u03bd\u03b7 - CNN GREECE", "url": "https://www.cnn.gr/ellada/story/246382/kakokairia-plimmyrise-i-akropoli-apo-tin-kataigida-ti-apanta-i-mendoni", "author": "Newsroom", "publishedAt": "2020-12-10T20:14:00Z", "content": ", . .\r\n . \u00ab \u00bb.\r\n. , , , \u00ab 2014 . 17 \u00bb. ' .\r\n , \u00ab \u00bb \u00ab \u00bb.", "source": {"id": null, "name": "Www.cnn.gr"}, "urlToImage": "https://cdn.cnngreece.gr/media/news/2020/12/10/246382/facebook/facebookAKROPOLI.jpg"}, {"description": "\u039f \u039f\u03bb\u03c5\u03bc\u03c0\u03b9\u03b1\u03ba\u03cc\u03c2 \u03b2\u03c1\u03ad\u03b8\u03b7\u03ba\u03b5 \u03bd\u03b1 \u03c7\u03ac\u03bd\u03b5\u03b9 \u03bc\u03b5 16 \u03c0\u03cc\u03bd\u03c4\u03bf\u03c5\u03c2, \u03b1\u03bb\u03bb\u03ac \u03c4\u03bf \u03b3\u03cd\u03c1\u03b9\u03c3\u03b5 \u03ba\u03b1\u03b9 \u03c0\u03ae\u03c1\u03b5 \u03b5\u03ba\u03c0\u03bb\u03b7\u03ba\u03c4\u03b9\u03ba\u03ae \u03bd\u03af\u03ba\u03b7 \u03b5\u03c0\u03af \u03c4\u03bf\u03c5 \u0395\u03c1\u03c5\u03b8\u03c1\u03bf\u03cd \u0391\u03c3\u03c4\u03ad\u03c1\u03b1 \u03bc\u03b5 79-81.", "title": "\u0395\u03c1\u03c5\u03b8\u03c1\u03cc\u03c2 \u0391\u03c3\u03c4\u03ad\u03c1\u03b1\u03c2 - \u039f\u03bb\u03c5\u03bc\u03c0\u03b9\u03b1\u03ba\u03cc\u03c2 79-81: \u0391\u03bd\u03b1\u03c4\u03c1\u03bf\u03c0\u03ae made in Olympiacos (vid) - gazzetta.gr", "url": "https://www.gazzetta.gr/basketball/euroleague/article/1542155/erythros-asteras-olympiakos-79-81-anatropi-made-olympiacos-vid", "author": "\u039a\u03c9\u03bd\u03c3\u03c4\u03b1\u03bd\u03c4\u03af\u03bd\u03bf\u03c2 \u039c\u03b5\u03bb\u03ac\u03b3\u03b9\u03b5\u03c2", "publishedAt": "2020-12-10T20:05:00Z", "content": "79-81. \u00ab\u00bb 16 , 1957.\r\n (, , ' ) (14-5, 5'). , . 6/8 +16 (30-14, 9').\r\n . \u00ab\u00bb (37-27, 15'). lay up (45-37, 20).\r\n . , . 3/3 52-50 (15'). , (52-54, 27'). \u00ab\u00bb (61-62, 30').\r\n , , , \u00a0 . +9 (61-70, 32'). 69\u2026 [+236 chars]", "source": {"id": null, "name": "Gazzetta.gr"}, "urlToImage": "https://www.gazzetta.gr/sites/default/files/styles/euroleague_ogimage_watermark/public/article/2020-12/5202776_1.jpg?itok=C9wrv47g"}, {"description": "\u03a0\u03bf\u03cd \u03b5\u03af\u03c3\u03c4\u03b5, \u03c1\u03b5 \u03c4\u03c1\u03cd\u03c0\u03b5\u03c2 \u03bd\u03b1 \u03bc\u03b1\u03c2 \u03c0\u03b5\u03af\u03c4\u03b5 \u03b3\u03b9\u03b1 \u03c4\u03bf\u03bd \u03a0\u0391\u039f\u039a \u03c0\u03bf\u03c5 \u03b4\u03b5\u03bd \u03bd\u03af\u03ba\u03b7\u03c3\u03b5 \u03bf\u03cd\u03c4\u03b5 \u03c4\u03ce\u03c1\u03b1...", "title": "\u039f\u03bb\u03bf\u03ba\u03bb\u03b7\u03c1\u03ce\u03b8\u03b7\u03ba\u03b5 \u03bf \u03b4\u03b9\u03b1\u03c3\u03c5\u03c1\u03bc\u03cc\u03c2 \u03c4\u03bf\u03c5 \u03a0\u0391\u039f\u039a! \u039f\u03c5\u03c3\u03c4, \u03c1\u03cc\u03bc\u03c0\u03b5\u03c2, \u03c0\u03bf\u03c5 \u03b8\u03b1 \u03c0\u03b5\u03af\u03c4\u03b5 \u03b3\u03b9\u03b1 \u03c4\u03bf\u03bd \u039f\u03bb\u03c5\u03bc\u03c0\u03b9\u03b1\u03ba\u03cc! - gavros.gr", "url": "https://www.gavros.gr/article/podosfairo/311610-oloklhrwthhke-o-diasyrmos-toy-paok-oyst-rompes-poy-tha-peite-gia-ton-olympiako", "author": null, "publishedAt": "2020-12-10T19:48:00Z", "content": "", "source": {"id": null, "name": "Gavros.gr"}, "urlToImage": "https://www.gavros.gr/photos/c_980px_500px_social/articles/202012/3043929.jpg"}, {"description": "\u0391\u03bc\u03b5\u03c1\u03b9\u03ba\u03b1\u03bd\u03b9\u03ba\u03ad\u03c2 \u03ba\u03c5\u03c1\u03ce\u03c3\u03b5\u03b9\u03c2 \u03b5\u03b9\u03c2 \u03b2\u03ac\u03c1\u03bf\u03c2 \u03c4\u03b7\u03c2 \u03a4\u03bf\u03c5\u03c1\u03ba\u03af\u03b1\u03c2 \u03b3\u03b9\u03b1 \u03c4\u03b7\u03bd \u03b1\u03b3\u03bf\u03c1\u03ac \u03c4\u03c9\u03bd \u03c1\u03c9\u03c3\u03b9\u03ba\u03ce\u03bd \u03c0\u03c5\u03c1\u03b1\u03c5\u03bb\u03b9\u03ba\u03ce\u03bd \u03b1\u03bc\u03c5\u03bd\u03c4\u03b9\u03ba\u03ce\u03bd \u03c3\u03c5\u03c3\u03c4\u03b7\u03bc\u03ac\u03c4\u03c9\u03bd S-400 \u03b8\u03b1 \u03b3\u03c5\u03c1\u03af\u03c3\u03bf\u03c5\u03bd \u03bc\u03c0\u03bf\u03cd\u03bc\u03b5\u03c1\u03b1\u03bd\u03b3\u03ba \u03ba\u03b1\u03b9 \u03b8\u03b1 \u03b2\u03bb\u03ac\u03c8\u03bf\u03c5\u03bd \u03c4\u03bf\u03c5\u03c2 \u03b4\u03b5\u03c3\u03bc\u03bf\u03cd\u03c2 \u03bc\u03b5\u03c4\u03b1\u03be\u03cd \u03c4\u03c9\u03bd \u03b4\u03cd\u03bf \u03bd\u03b1\u03c4\u03bf\u03ca\u03ba\u03ce\u03bd \u03c3\u03c5\u03bc\u03bc\u03ac\u03c7\u03c9\u03bd, \u03b4\u03ae\u03bb\u03c9\u03c3\u03b5 \u03c3\u03ae\u03bc\u03b5\u03c1\u03b1 \u03ad\u03bd\u03b1\u03c2 \u03b1\u03bd\u03ce\u03c4\u03b5\u03c1\u03bf\u03c2 \u03a4\u03bf\u03cd\u03c1\u03ba\u03bf\u03c2 \u03b1\u03be\u03b9\u03c9\u03bc\u03b1\u03c4\u03bf\u03cd\u03c7\u03bf\u03c2.\u0395\u03c0\u03b9\u03ba\u03b1\u03bb\u03bf\u03cd\u03bc\u03b5\u03bd\u03bf \u03c4\u03ad\u2026", "title": "\u0388\u03be\u03b1\u03bb\u03bb\u03b7 \u03b7 \u03a4\u03bf\u03c5\u03c1\u03ba\u03af\u03b1 \u03b3\u03b9\u03b1 \u03c4\u03b9\u03c2 \u0391\u03bc\u03b5\u03c1\u03b9\u03ba\u03b1\u03bd\u03b9\u03ba\u03ad\u03c2 \u03ba\u03c5\u03c1\u03ce\u03c3\u03b5\u03b9\u03c2: \"\u0398\u03b1 \u03b3\u03c5\u03c1\u03af\u03c3\u03bf\u03c5\u03bd \u03bc\u03c0\u03bf\u03cd\u03bc\u03b5\u03c1\u03b1\u03bd\u03b3\u03ba\" - Skai.gr", "url": "https://www.skai.gr/news/world/eksalli-i-tourkia-gia-tis-amerikanikes-kyroseis-tha-gyrisoun-mpoumerangk", "author": "\u0391\u03a0\u0395-\u039c\u03a0\u0395", "publishedAt": "2020-12-10T19:27:00Z", "content": "", "source": {"id": null, "name": "Skai.gr"}, "urlToImage": "https://www.skai.gr/sites/default/files/styles/large/public/2020-06/simaia-tourkia-stratiotis-ap.jpg?itok=2B5AKL1j"}, {"description": "\u03a4\u03b1 \u03c3\u03c7\u03ad\u03b4\u03b9\u03b1 \u03b1\u03bd\u03b1\u03b2\u03ac\u03bb\u03bb\u03bf\u03bd\u03c4\u03b1\u03b9, \u03b5\u03c0\u03b5\u03b9\u03b4\u03ae \u03c4\u03b1 \u03ba\u03c1\u03bf\u03cd\u03c3\u03bc\u03b1\u03c4\u03b1 \u03b4\u03b5\u03bd \u03ad\u03c7\u03bf\u03c5\u03bd \u03c0\u03ad\u03c3\u03b5\u03b9 \u03c3\u03c4\u03bf \u03b5\u03c0\u03b9\u03b8\u03c5\u03bc\u03b7\u03c4\u03cc \u03b5\u03c0\u03af\u03c0\u03b5\u03b4\u03bf", "title": "\u0393\u03b1\u03bb\u03bb\u03af\u03b1: \u00ab\u03a6\u03c1\u03ad\u03bd\u03bf\u00bb \u03c3\u03c4\u03b7\u03bd \u03ac\u03c1\u03c3\u03b7 \u03c4\u03bf\u03c5 lockdown- \u0394\u03b5\u03bd \u03b1\u03bd\u03bf\u03af\u03b3\u03bf\u03c5\u03bd \u03b8\u03ad\u03b1\u03c4\u03c1\u03b1, \u03bc\u03bf\u03c5\u03c3\u03b5\u03af\u03b1 \u03ba\u03b1\u03b9 \u03ba\u03b9\u03bd\u03b7\u03bc\u03b1\u03c4\u03bf\u03b3\u03c1\u03ac\u03c6\u03bf\u03b9 - LiFO mobile", "url": "https://www.lifo.gr/now/world/306012/gallia-freno-stin-arsi-toy-lockdown-den-anoigoyn-theatra-moyseia-kai-kinimatografoi", "author": null, "publishedAt": "2020-12-10T19:15:00Z", "content": "\u00ab\u00bb lockdown, 5.000 , .\r\n , , , , , .\r\n 15 lockdown, , . , 5.000.\r\n\u00ab 15 \u00bb, . \u00ab . \u00bb, . , , , .\r\n, 15 . , 20:00 , . , , , .\r\nLiFO.gr Google News\r\n , LiFO.gr", "source": {"id": null, "name": "Lifo.gr"}, "urlToImage": "https://www.lifo.gr/icache/1200/630/2_3058397870/1687735_louvre.jpg"}, {"description": "\u0397 \u038c\u03bb\u03b3\u03b1 \u039a\u03b5\u03c6\u03b1\u03bb\u03bf\u03b3\u03b9\u03ac\u03bd\u03bd\u03b7 \u03b1\u03c0\u03bf\u03c7\u03b1\u03b9\u03c1\u03ad\u03c4\u03b7\u03c3\u03b5 \u03c4\u03b7 \u03b8\u03b5\u03af\u03b1 \u03c4\u03b7\u03c2 \u039b\u03ae\u03b4\u03b1 \u039a\u03b1\u03c4\u03b1\u03ba\u03bf\u03c5\u03b6\u03b7\u03bd\u03bf\u03cd - \u0392\u03b1\u03c1\u03b4\u03b9\u03bd\u03bf\u03b3\u03b9\u03ac\u03bd\u03bd\u03b7 \u03bc\u03b5 \u03bc\u03af\u03b1 \u03c3\u03c5\u03b3\u03ba\u03b9\u03bd\u03b7\u03c4\u03b9\u03ba\u03ae \u03b1\u03bd\u03ac\u03c1\u03c4\u03b7\u03c3\u03b7", "title": "\u03a0\u03ad\u03b8\u03b1\u03bd\u03b5 \u03b7 \u039b\u03ae\u03b4\u03b1 \u0392\u03b1\u03c1\u03b4\u03b9\u03bd\u03bf\u03b3\u03b9\u03ac\u03bd\u03bd\u03b7 - \u0397 \u03c3\u03c5\u03b3\u03ba\u03b9\u03bd\u03b7\u03c4\u03b9\u03ba\u03ae \u03b1\u03bd\u03ac\u03c1\u03c4\u03b7\u03c3\u03b7 \u03c4\u03b7\u03c2 \u038c\u03bb\u03b3\u03b1\u03c2 \u039a\u03b5\u03c6\u03b1\u03bb\u03bf\u03b3\u03b9\u03ac\u03bd\u03bd\u03b7 - \u0388\u03b8\u03bd\u03bf\u03c2", "url": "https://www.ethnos.gr/ellada/136889_pethane-i-lida-bardinogianni-i-sygkinitiki-anartisi-tis-olgas-kefalogianni", "author": null, "publishedAt": "2020-12-10T19:03:49Z", "content": ", 91 , - , . \u00a0 Instagram.\u00ab - , , grande dame , , , , , , , . !\u00ab \u00bb 2014 ( . -), , \u00bb, \u00a0 \u00a0\u00a0.", "source": {"id": null, "name": "Ethnos.gr"}, "urlToImage": "https://www.ethnos.gr/sites/default/files/styles/og_image/public/images/2020/12/130695520_1735528716628826_3117333688482693631_n.png?itok=QyE_IOpy"}, {"description": "\u0397 \u03c0\u03bb\u03b5\u03b9\u03bf\u03bd\u03cc\u03c4\u03b7\u03c4\u03b1 \u03c4\u03c9\u03bd \u03b5\u03c1\u03c9\u03c4\u03b7\u03b8\u03ad\u03bd\u03c4\u03c9\u03bd \u03ba\u03ac\u03bd\u03b5\u03b9 \u03bb\u03cc\u03b3\u03bf \u03b3\u03b9\u03b1 \u03ba\u03b1\u03b8\u03c5\u03c3\u03c4\u03b5\u03c1\u03b7\u03bc\u03ad\u03bd\u03b7 \u03bb\u03ae\u03c8\u03b7 \u03bc\u03ad\u03c4\u03c1\u03c9\u03bd \u03b1\u03c0\u03cc \u03c4\u03b7\u03bd \u03ba\u03c5\u03b2\u03ad\u03c1\u03bd\u03b7\u03c3\u03b7. \u0391\u03c1\u03bd\u03b7\u03c4\u03b9\u03ba\u03ae \u03b5\u03b9\u03ba\u03cc\u03bd\u03b1 \u03b3\u03b9\u03b1 \u03c0\u03bf\u03bb\u03bb\u03bf\u03cd\u03c2 \u03c5\u03c0\u03bf\u03c5\u03c1\u03b3\u03bf\u03cd\u03c2.", "title": "\u0394\u03b7\u03bc\u03bf\u03c3\u03ba\u03cc\u03c0\u03b7\u03c3\u03b7: \u039f\u03b9 \u03c0\u03bf\u03bb\u03af\u03c4\u03b5\u03c2 \u03b4\u03b5\u03bd \u03c3\u03c5\u03bc\u03c6\u03c9\u03bd\u03bf\u03cd\u03bd \u03bc\u03b5 \u03c4\u03b1 \u03ba\u03c5\u03b2\u03b5\u03c1\u03bd\u03b7\u03c4\u03b9\u03ba\u03ac \u03bc\u03ad\u03c4\u03c1\u03b1 \u03b3\u03b9\u03b1 \u03c4\u03b7\u03bd \u03c0\u03b1\u03bd\u03b4\u03b7\u03bc\u03af\u03b1 - \u0397 \u0395\u03c6\u03b7\u03bc\u03b5\u03c1\u03af\u03b4\u03b1 \u03c4\u03c9\u03bd \u03a3\u03c5\u03bd\u03c4\u03b1\u03ba\u03c4\u03ce\u03bd", "url": "https://www.efsyn.gr/politiki/272377_dimoskopisi-oi-polites-den-symfonoyn-me-ta-kybernitika-metra-gia-tin-pandimia", "author": null, "publishedAt": "2020-12-10T19:03:04Z", "content": ", .\u00a0\r\n, Alco Open,\u00a0 54% , 40% . , 84% .\u00a0\r\n , . , 46% , , 31% , 18%\u00a0 .\u00a0\r\n, , ( ) .\u00a0\r\n , \u00a0 (42%),\u00a0 (33%) , 19% . .\r\n, 64% , 24% .\r\n, .. (38%) (22,6%), .. (6,9%), (5,6%) (4,2%).\r\n 1.000 , +/-3,1% 3 9 .", "source": {"id": null, "name": "Efsyn.gr"}, "urlToImage": "https://www.efsyn.gr/sites/default/files/styles/default/public/2020-11/mitsotakis-kikilias.jpg?itok=5qqTUN42"}, {"description": "\u0394\u03c5\u03c3\u03b1\u03c1\u03b5\u03c3\u03c4\u03b7\u03bc\u03ad\u03bd\u03b7 \u03b7 \u03b5\u03bb\u03bb\u03b7\u03bd\u03b9\u03ba\u03ae \u03c0\u03bb\u03b5\u03c5\u03c1\u03ac \u03bc\u03b5 \u03c4\u03bf \u03c0\u03c1\u03bf\u03c3\u03c7\u03ad\u03b4\u03b9\u03bf \u03c4\u03bf\u03c5 \u03ba\u03b5\u03b9\u03bc\u03ad\u03bd\u03bf\u03c5 \u03c3\u03c5\u03bc\u03c0\u03b5\u03c1\u03b1\u03c3\u03bc\u03ac\u03c4\u03c9\u03bd \u03c4\u03b7\u03c2 \u03a3\u03c5\u03bd\u03cc\u03b4\u03bf\u03c5 \u039a\u03bf\u03c1\u03c5\u03c6\u03ae\u03c2. \u03a0\u03bf\u03b9\u03b5\u03c2 \u03c7\u03ce\u03c1\u03b5\u03c2 \u03b8\u03ad\u03bb\u03bf\u03c5\u03bd \u03ba\u03c5\u03c1\u03ce\u03c3\u03b5\u03b9\u03c2 \u03c3\u03c4\u03b7\u03bd \u03a4\u03bf\u03c5\u03c1\u03ba\u03af\u03b1 \u03ba\u03b1\u03b9 \u03c0\u03bf\u03b9\u03b5\u03c2 \u03cc\u03c7\u03b9. \u03a4\u03b1 \u03c7\u03c1\u03bf\u03bd\u03bf\u03b4\u03b9\u03b1\u03b3\u03c1\u03ac\u03bc\u03bc\u03b1\u03c4\u03b1 \u03c4\u03bf\u03c5 \u03a6\u03b5\u03b2\u03c1\u03bf\u03c5\u03b1\u03c1\u03af\u03bf\u03c5 \u03ba\u03b1\u03b9 \u03c4\u03bf\u03c5 \u039c\u03b1\u03c1\u03c4\u03af\u03bf\u03c5.", "title": "\u03a3\u03c4\u03bf\u03bd \u03b1\u03ad\u03c1\u03b1 \u03bf\u03b9 \u03ba\u03c5\u03c1\u03ce\u03c3\u03b5\u03b9\u03c2 \u03c3\u03c4\u03b7\u03bd \u03a4\u03bf\u03c5\u03c1\u03ba\u03af\u03b1 - \u039c\u03ac\u03c7\u03b7 \u03c3\u03c4\u03bf \u03b4\u03b5\u03af\u03c0\u03bd\u03bf \u03c4\u03c9\u03bd 27 \u03c4\u03b7\u03c2 \u0395\u0395 \u03b3\u03b9\u03b1 \u03bd\u03b1 \u03b1\u03bb\u03bb\u03ac\u03be\u03b5\u03b9 \u03c4\u03bf \u03c0\u03c1\u03bf\u03c3\u03c7\u03ad\u03b4\u03b9\u03bf - \u03a0\u03bf\u03bb\u03b9\u03c4\u03b9\u03ba\u03ae | News 24/7 - News247.gr", "url": "https://www.news247.gr/politiki/ston-aera-oi-kyroseis-stin-toyrkia-machi-sto-deipno-ton-27-tis-ee-gia-na-allaxei-to-proschedio.9077103.html", "author": "\u0392\u03af\u03ba\u03c5 \u03a3\u03b1\u03bc\u03b1\u03c1\u03ac", "publishedAt": "2020-12-10T18:51:00Z", "content": "27 , .\r\n .\r\n . . , . .\r\n . : , : .\r\n : , , . , .\r\n : , , . Pacta sunt servanda.\r\n , , , , , . , . 90 .\r\n, , , . , , .\r\n . , . .\r\n , , , .\r\n twitter , 27 , , 2022.\r\n \u00a0\u00a0 , \u00a0News247.gr", "source": {"id": null, "name": "News247.gr"}, "urlToImage": "https://www.news247.gr/img/3680/9077111/293000/fb1200/1200/sinodos101220.jpg"}, {"description": "\u0397 \u03b4\u03b9\u03ac\u03c3\u03b7\u03bc\u03b7 \u03c4\u03b1\u03b9\u03bd\u03af\u03b1 \u03c4\u03bf\u03c5 \u0393\u03b9\u03ac\u03bd\u03bd\u03b7 \u039f\u03b9\u03ba\u03bf\u03bd\u03bf\u03bc\u03af\u03b4\u03b7 \u03b8\u03b1 \u03c0\u03c1\u03bf\u03b2\u03bb\u03b7\u03b8\u03b5\u03af \u03c3\u03c4\u03b9\u03c2 25/12, 26/12 \u03ba\u03b1\u03b9 27/12 online. \u039f\u03b9 \u03b8\u03b5\u03b1\u03c4\u03ad\u03c2 \u03b8\u03b1 \u03bc\u03c0\u03bf\u03c1\u03bf\u03cd\u03bd \u03bd\u03b1 \u03b1\u03c0\u03bf\u03bb\u03b1\u03cd\u03c3\u03bf\u03c5\u03bd \u03c4\u03b7\u03bd \u03c4\u03b1\u03b9\u03bd\u03af\u03b1 \u03b1\u03c0\u03cc \u03c4\u03b7\u03bd \u03ac\u03bd\u03b5\u03c3\u03b7 \u03c4\u03bf\u03c5 \u03c3\u03c0\u03b9\u03c4\u03b9\u03bf\u03cd \u03c4\u03bf\u03c5\u03c2.", "title": "Online \u03c0\u03c1\u03bf\u03b2\u03bf\u03bb\u03ad\u03c2 \u03c4\u03b7\u03c2 \u03c4\u03b1\u03b9\u03bd\u03af\u03b1\u03c2 '\u0397 \u03bc\u03c0\u03b1\u03bb\u03ac\u03bd\u03c4\u03b1 \u03c4\u03b7\u03c2 \u03c4\u03c1\u03cd\u03c0\u03b9\u03b1\u03c2 \u03ba\u03b1\u03c1\u03b4\u03b9\u03ac\u03c2' - Good News | News 24/7 - News247.gr", "url": "https://www.news247.gr/good-news/online-provoles-tis-tainias-i-mpalanta-tis-trypias-kardias.9077036.html", "author": "News 24/7", "publishedAt": "2020-12-10T18:06:00Z", "content": ", , \u00ab \u00bb online 4 Viva.gr.\r\n Ultra HD (4) 25/12, 26/12 27/12 (12:00, 18:00 22:00).\r\n 5 .\r\n .\r\n \u00ab \u00bb, \u00ab\u00bb, \u00ab \u00bb, \u00ab\u00bb \u00ab \u00bb, \u00ab\u00bb , , , \u00ab\u00bb , .\r\n , , , . .\r\n , , , , , , , \r\n , News247.gr", "source": {"id": null, "name": "News247.gr"}, "urlToImage": "https://www.news247.gr/img/3885/9077072/053000/fb1200/1200/bisbikis.jpg"}, {"description": "\u03a6\u03c9\u03c4\u03bf\u03b3\u03c1\u03b1\u03c6\u03af\u03b5\u03c2 \u03b1\u03c0\u03cc \u03c4\u03b7\u03bd \u03c3\u03c4\u03bf\u03bb\u03b9\u03c3\u03bc\u03ad\u03bd\u03b7 \u03c0\u03bb\u03b1\u03c4\u03b5\u03af\u03b1 \u039f\u03bc\u03bf\u03bd\u03bf\u03af\u03b1\u03c2", "title": "\u03a3\u03c4\u03bf\u03bb\u03af\u03c3\u03c4\u03b7\u03ba\u03b5 \u03b7 \u039f\u03bc\u03cc\u03bd\u03bf\u03b9\u03b1: \u03a7\u03c1\u03b9\u03c3\u03c4\u03bf\u03c5\u03b3\u03b5\u03bd\u03bd\u03b9\u03ac\u03c4\u03b9\u03ba\u03bf \u03b4\u03ad\u03bd\u03c4\u03c1\u03bf 15 \u03bc\u03ad\u03c4\u03c1\u03c9\u03bd \u03b4\u03af\u03c0\u03bb\u03b1 \u03c3\u03c4\u03bf \u03c3\u03b9\u03bd\u03c4\u03c1\u03b9\u03b2\u03ac\u03bd\u03b9 - LiFO mobile", "url": "https://www.lifo.gr/now/greece/306005/stolistike-i-omonoia-xristoygenniatiko-dentro-15-metron-dipla-sto-sintrivani", "author": null, "publishedAt": "2020-12-10T17:56:00Z", "content": null, "source": {"id": null, "name": "Lifo.gr"}, "urlToImage": "https://www.lifo.gr/icache/1200/630/2_3058397870/1687709_\u03bf\u03bc\u03bf\u03bd\u03bf\u03b9\u03b1-3.jpg"}, {"description": "\u0397 \u03bb\u03b1\u03ca\u03ba\u03ae \u03b1\u03c0\u03b1\u03af\u03c4\u03b7\u03c3\u03b7 \u03b3\u03b9\u03b1 \u03c0\u03b1\u03c1\u03b1\u03af\u03c4\u03b7\u03c3\u03b7 \u03c4\u03bf\u03c5 \u03a5\u03c0\u03bf\u03c5\u03c1\u03b3\u03bf\u03cd \u0395\u03c3\u03c9\u03c4\u03b5\u03c1\u03b9\u03ba\u03ce\u03bd \u03c3\u03c4\u03b7\u03bd \u0391\u03bb\u03b2\u03b1\u03bd\u03af\u03b1 \u03ad\u03b3\u03b9\u03bd\u03b5 \u03c0\u03c1\u03ac\u03be\u03b7. \u039f \u03a1\u03ac\u03bc\u03b1 \u03b8\u03b1 \u03c4\u03b7\u03bd \u03b5\u03bd\u03b5\u03c1\u03b3\u03bf\u03c0\u03bf\u03b9\u03ae\u03c3\u03b5\u03b9 \u03bc\u03cc\u03bb\u03b9\u03c2 \u03b5\u03c0\u03b9\u03c3\u03c4\u03c1\u03ad\u03c8\u03b5\u03b9 \u03b1\u03c0\u03cc \u03c4\u03b9\u03c2 \u0397\u03a0\u0391.", "title": "\u0391\u03bb\u03b2\u03b1\u03bd\u03af\u03b1: \u03a0\u03b1\u03c1\u03b1\u03b9\u03c4\u03ae\u03b8\u03b7\u03ba\u03b5 \u03bf \u03a5\u03c0\u03bf\u03c5\u03c1\u03b3\u03cc\u03c2 \u0395\u03c3\u03c9\u03c4\u03b5\u03c1\u03b9\u03ba\u03ce\u03bd, \u03c0\u03c1\u03ce\u03c4\u03b7 \u03bd\u03af\u03ba\u03b7 \u03c4\u03c9\u03bd \u03b4\u03b9\u03b1\u03b4\u03b7\u03bb\u03c9\u03c4\u03ce\u03bd - \u039a\u03cc\u03c3\u03bc\u03bf\u03c2 | News 24/7 - News247.gr", "url": "https://www.news247.gr/kosmos/alvania-paraitithike-o-ypoyrgos-esoterikon-proti-niki-ton-diadiloton.9077047.html", "author": "News 24/7", "publishedAt": "2020-12-10T17:52:00Z", "content": "25 \r\n AP\r\n. . \r\nO , . \r\n (10/12), 25.\r\n\" \", , . \" \", .\r\n , .\r\n 25 . . , , . . , , . \r\n .\r\n, , , , , .\r\n , , , .\r\n 25 , , , . , . .\r\n 8 , , . , .\r\n , News247.gr\r\nSHARE:Newsletter\r\n email", "source": {"id": null, "name": "News247.gr"}, "urlToImage": "https://www.news247.gr/img/8275/9076074/441000/fb1200/1200/albania2.jpg"}, {"description": "", "title": "\u03a3\u03c4\u03b1\u03c4\u03b9\u03c3\u03c4\u03b9\u03ba\u03ac \u03c3\u03c4\u03bf\u03b9\u03c7\u03b5\u03af\u03b1 \u03c4\u03c9\u03bd \u03b4\u03b7\u03bb\u03ce\u03c3\u03b5\u03c9\u03bd Covid, \u039c\u03b1\u03c1\u03c4\u03af\u03bf\u03c5 - \u0391\u03c5\u03b3\u03bf\u03cd\u03c3\u03c4\u03bf\u03c5 2020, \u03b3\u03b9\u03b1 \u03c4\u03b7\u03bd \u03ad\u03ba\u03c0\u03c4\u03c9\u03c3\u03b7 \u03c6\u03cc\u03c1\u03bf\u03c5 \u03c3\u03c4\u03bf\u03c5\u03c2 \u03b5\u03ba\u03bc\u03b9\u03c3\u03b8\u03c9\u03c4\u03ad\u03c2 \u03b1\u03ba\u03b9\u03bd\u03ae\u03c4\u03c9\u03bd - Taxheaven.gr", "url": "https://www.taxheaven.gr/news/51958/statistika-stoixeia-twn-dhlwsewn-covid-martioy-aygoystoy-2020-gia-thn-ekptwsh-foroy-stoys-ekmisowtes-akinhtwn", "author": "Taxheaven Newsroom", "publishedAt": "2020-12-10T17:36:07Z", "content": "Unfortunately this feature requires cookies currently not allowed by your settings. You may click here to change them if you wish to use this feature.", "source": {"id": null, "name": "Taxheaven.gr"}, "urlToImage": "https://www.taxheaven.gr/uploads/images//aade_statistics03.jpg"}, {"description": "\u039c\u03b9\u03b1 \u03b1\u03c0\u03bf\u03c7\u03ce\u03c1\u03b7\u03c3\u03b7-\u03b1\u03bd\u03b1\u03c4\u03c1\u03bf\u03c0\u03ae \u03c6\u03b1\u03af\u03bd\u03b5\u03c4\u03b1\u03b9 \u03cc\u03c4\u03b9 \u03b8\u03b1 \u03b4\u03bf\u03cd\u03bc\u03b5 \u03c3\u03c4\u03b7\u03bd \u03b1\u03c5\u03c1\u03b9\u03b1\u03bd\u03ae \u03c4\u03b5\u03bb\u03b5\u03c4\u03ae \u03c4\u03c9\u03bd \u03c1\u03cc\u03b4\u03c9\u03bd \u03c3\u03c4\u03bf The Bachelor.\u039f \u03a0\u03b1\u03bd\u03b1\u03b3\u03b9\u03ce\u03c4\u03b7\u03c2 \u0392\u03b1\u03c3\u03b9\u03bb\u03ac\u03ba\u03bf\u03c2", "title": "The Bachelor - Spoiler: \u0391\u03bd\u03b1\u03c4\u03c1\u03bf\u03c0\u03ae! \u03a0\u03bf\u03b9\u03bf \u03c6\u03b1\u03b2\u03bf\u03c1\u03af \u03b4\u03b5\u03bd \u03b8\u03b1 \u03c0\u03ac\u03c1\u03b5\u03b9 \u03c4\u03c1\u03b9\u03b1\u03bd\u03c4\u03ac\u03c6\u03c5\u03bb\u03bb\u03bf \u03ba\u03b1\u03b9 \u03b4\u03b5\u03bd \u03b8\u03b1 \u03c6\u03c4\u03ac\u03c3\u03b5\u03b9 \u03c3\u03c4\u03bf\u03bd \u03c4\u03b5\u03bb\u03b9\u03ba\u03cc - Znews", "url": "https://znews.gr/media/reality/the-bachelor-spoiler-anatropi-poio-favori-den-tha-parei-triantafyllo-kai-den-tha-ftasei-ston-teliko/", "author": "", "publishedAt": "2020-12-10T17:29:54Z", "content": "!\r\n , showbiz . , , , - , , opinions , , .", "source": {"id": null, "name": "Znews.gr"}, "urlToImage": "https://znews.gr/wp-content/uploads/2020/12/129486096_175753087555399_1809912056518401494_o-e1607620634509.jpg"}, {"description": "\u03a3\u03c4\u03b9\u03c2 17 \u03c7\u03b9\u03bb\u03b9\u03ac\u03b4\u03b5\u03c2 \u03c4\u03b1 \u03bd\u03ad\u03b1 \u03ba\u03c1\u03bf\u03cd\u03c3\u03bc\u03b1\u03c4\u03b1 \u03ba\u03bf\u03c1\u03c9\u03bd\u03bf\u03ca\u03bf\u03cd \u03c3\u03c4\u03b7\u03bd \u0399\u03c4\u03b1\u03bb\u03af\u03b1 - \u039a\u03bf\u03bd\u03c4\u03ac \u03c3\u03c4\u03b9\u03c2 3.300 \u03bf\u03b9 \u03bd\u03bf\u03c3\u03b7\u03bb\u03b5\u03c5\u03cc\u03bc\u03b5\u03bd\u03bf\u03b9 \u03c3\u03b5 \u039c\u0395\u0398 | \u039a\u03bf\u03c1\u03c9\u03bd\u03bf\u03ca\u03cc\u03c2 | \u039d\u03b5\u03ba\u03c1\u03bf\u03af \u03b1\u03c0\u03cc \u03ba\u03bf\u03c1\u03c9\u03bd\u03bf\u03ca\u03cc | \u0399\u03c4\u03b1\u03bb\u03af\u03b1 | \u039a\u03c1\u03bf\u03cd\u03c3\u03bc\u03b1\u03c4\u03b1 \u03ba\u03bf\u03c1\u03c9\u03bd\u03bf\u03ca\u03bf\u03cd | \u039a\u03bf\u03c1\u03c9\u03bd\u03bf\u03ca\u03cc\u03c2 LIVE", "title": "\u039a\u03bf\u03c1\u03c9\u03bd\u03bf\u03ca\u03cc\u03c2 - \u03a3\u03c5\u03bd\u03b5\u03c7\u03af\u03b6\u03b5\u03c4\u03b1\u03b9 \u03b7 \u03c4\u03c1\u03b1\u03b3\u03c9\u03b4\u03af\u03b1 \u03c3\u03c4\u03b7\u03bd \u0399\u03c4\u03b1\u03bb\u03af\u03b1: \u0386\u03b3\u03b3\u03b9\u03be\u03b1\u03bd \u03c4\u03bf\u03c5\u03c2 900 \u03bf\u03b9 \u03bd\u03ad\u03bf\u03b9 \u03b8\u03ac\u03bd\u03b1\u03c4\u03bf\u03b9 - \u03a0\u03c1\u03ce\u03c4\u03bf \u0398\u03ad\u03bc\u03b1", "url": "https://www.protothema.gr/koronoios-live/article/1073743/koronoios-sunehizetai-i-tragodia-stin-italia-aggixan-tous-900-oi-neoi-thanatoi/", "author": "\u03a0\u03c1\u03ce\u03c4\u03bf \u0398\u03ad\u03bc\u03b1", "publishedAt": "2020-12-10T17:10:00Z", "content": "Covid-19 , . , 24 887 499, 62.626.\r\n, 16.999171.586 , 12.756 118.475 . 3.291, 29 ., , (4.197, 2.093 1.488 ).\r\n :\r\n: - \r\n Facebook\r\n \u00ab \u00bb", "source": {"id": null, "name": "Protothema.gr"}, "urlToImage": "https://i1.prth.gr/images/640x360share/files/2020-11-23/italia_meth.jpg"}, {"description": "\u03a4\u03b1 \u03bc\u03ad\u03c4\u03c1\u03b1 \u03c0\u03bf\u03c5 \u03b8\u03b1 \u03b9\u03c3\u03c7\u03cd\u03c3\u03bf\u03c5\u03bd \u03b5\u03bd\u03cc\u03c8\u03b5\u03b9 \u03c4\u03c9\u03bd \u03b5\u03bf\u03c1\u03c4\u03ce\u03bd \u03b8\u03b1 \u03c0\u03b1\u03c1\u03bf\u03c5\u03c3\u03b9\u03b1\u03c3\u03c4\u03bf\u03cd\u03bd \u03b1\u03cd\u03c1\u03b9\u03bf \u03a0\u03b1\u03c1\u03b1\u03c3\u03ba\u03b5\u03c5\u03ae \u03c3\u03c4\u03b9\u03c2 11 \u03c4\u03bf \u03c0\u03c1\u03c9\u03af \u03ba\u03b1\u03c4\u03ac \u03c4\u03b7\u03bd \u03b5\u03bd\u03b7\u03bc\u03ad\u03c1\u03c9\u03c3\u03b7 \u03c4\u03c9\u03bd \u03c0\u03bf\u03bb\u03b9\u03c4\u03b9\u03ba\u03ce\u03bd \u03c3\u03c5\u03bd\u03c4\u03b1\u03ba\u03c4\u03ce\u03bd, \u03c0\u03bf\u03c5 \u03b8\u03b1 \u03c0\u03c1\u03b1\u03b3\u03bc\u03b1\u03c4\u03bf\u03c0\u03bf\u03b9\u03b7\u03b8\u03b5\u03af \u03b5\u03be \u03b1\u03c0\u03bf\u03c3\u03c4\u03ac\u03c3\u03b5\u03c9\u03c2. \u0395\u03ba\u03c4\u03cc\u03c2 \u03b1\u03c0\u03cc \u03c4\u03bf\u03bd \u03ba\u03c5\u03b2\u03b5\u03c1\u03bd\u03b7\u03c4\u03b9\u03ba\u03cc \u03b5\u03ba\u03c0\u03c1\u03cc\u03c3\u03c9\u03c0\u03bf \u03a3\u03c4\u03ad\u03bb\u03b9\u03bf \u03a0\u03ad\u03c4\u03c3\u03b1 \u03c3\u03c4\u03b7\u03bd \u03b5\u03bd\u03b7\u03bc\u03ad\u03c1\u03c9\u03c3\u03b7 \u03b8\u03b1 \u03c3\u03c5\u03bc\u03bc\u03b5\u03c4\u03ad\u03c7\u03b5\u03b9 \u03ba\u03b1\u03b9 \u03bf \u03c5\u2026", "title": "Lockdown: \u03a3\u03c4\u03b9\u03c2 11 \u03c4\u03bf \u03c0\u03c1\u03c9\u03af \u03c4\u03b7\u03c2 \u03a0\u03b1\u03c1\u03b1\u03c3\u03ba\u03b5\u03c5\u03ae\u03c2 \u03bf\u03b9 \u03b1\u03bd\u03b1\u03ba\u03bf\u03b9\u03bd\u03ce\u03c3\u03b5\u03b9\u03c2 \u03b1\u03c0\u03cc \u03a0\u03ad\u03c4\u03c3\u03b1 \u03ba\u03b1\u03b9 \u0393\u03b5\u03c9\u03c1\u03b3\u03b9\u03ac\u03b4\u03b7 - \u03a4\u03b9 \u03b1\u03bd\u03bf\u03af\u03b3\u03b5\u03b9 - Skai.gr", "url": "https://www.skai.gr/news/greece/lockdown-stis-11-to-proi-oi-anakoinoseis-apo-petsa-kai-georgiadi-ti-anoigei", "author": "\u03a3\u039a\u0391\u03aa", "publishedAt": "2020-12-10T16:52:00Z", "content": "11 , . , .\r\n , , .\r\n, .\r\n, , , ( ), (click away). , , \u00a0 . \u00a0\r\n 14 , .\r\n: skai.gr", "source": {"id": null, "name": "Skai.gr"}, "urlToImage": "https://www.skai.gr/sites/default/files/styles/large/public/2020-12/lockdown-monastiraki-it.jpg?itok=THZiIKhX"}, {"description": "\u0395\u03c0\u03b9\u03bc\u03ad\u03bd\u03b5\u03b9 \u03b7 \u03c0\u03b1\u03bd\u03b4\u03b7\u03bc\u03af\u03b1 \u03c4\u03bf\u03c5 \u03ba\u03bf\u03c1\u03bf\u03bd\u03bf\u03ca\u03bf\u03cd \u03c3\u03c4\u03b7 \u03c7\u03ce\u03c1\u03b1 \u03bc\u03b1\u03c2, \u03c0\u03b1\u03c1\u03ac \u03c4\u03bf lockdown \u03ba\u03b1\u03b9 \u03c4\u03b1 \u03c0\u03b5\u03c1\u03b9\u03bf\u03c1\u03b9\u03c3\u03c4\u03b9\u03ba\u03ac \u03bc\u03ad\u03c4\u03c1\u03b1 \u03c0\u03bf\u03c5 \u03b2\u03c1\u03af\u03c3\u03ba\u03bf\u03bd\u03c4\u03b1\u03b9 \u03c3\u03b5 \u03b9\u03c3\u03c7\u03cd \u03b5\u03b4\u03ce \u03ba\u03b1\u03b9 \u03c3\u03c7\u03b5\u03b4\u03cc\u03bd 5\u00a0\u03b5\u03b2\u03b4\u03bf\u03bc\u03ac\u03b4\u03b5\u03c2.", "title": "\u03a3\u03b5 \u03c5\u03c8\u03b7\u03bb\u03ac \u03b5\u03c0\u03af\u03c0\u03b5\u03b4\u03b1 \u03c0\u03b1\u03c1\u03b1\u03bc\u03ad\u03bd\u03bf\u03c5\u03bd \u03ba\u03c1\u03bf\u03cd\u03c3\u03bc\u03b1\u03c4\u03b1, \u03b8\u03ac\u03bd\u03b1\u03c4\u03bf\u03b9 \u03ba\u03b1\u03b9 \u03b4\u03b9\u03b1\u03c3\u03c9\u03bb\u03b7\u03bd\u03c9\u03bc\u03ad\u03bd\u03bf\u03b9 - \u0397 \u0395\u03c6\u03b7\u03bc\u03b5\u03c1\u03af\u03b4\u03b1 \u03c4\u03c9\u03bd \u03a3\u03c5\u03bd\u03c4\u03b1\u03ba\u03c4\u03ce\u03bd", "url": "https://www.efsyn.gr/ellada/ygeia/272363_se-ypsila-epipeda-paramenoyn-kroysmata-thanatoi-kai-diasolinomenoi", "author": null, "publishedAt": "2020-12-10T16:36:40Z", "content": "1534 , 23 . 121253, 52.7% .\r\n5066 (4.2%) 34181 (28.2%) .\r\n571 . 66 . 166 (29.1%) . To 76.7%, , 70 . 697 .\r\n, 81 3370 . 1351 (40.1%) . 79 96.0% / 70 .", "source": {"id": null, "name": "Efsyn.gr"}, "urlToImage": "https://www.efsyn.gr/sites/default/files/styles/default/public/2020-12/maskes_0.jpg?itok=geX3jEjE"}, {"description": "", "title": "\u0395\u03c0\u03b9\u03c3\u03c4\u03c1\u03b5\u03c0\u03c4\u03ad\u03b1 \u03a0\u03c1\u03bf\u03ba\u03b1\u03c4\u03b1\u03b2\u03bf\u03bb\u03ae 4: \u03a0\u03af\u03c3\u03c4\u03c9\u03c3\u03b7 \u03c0\u03bf\u03c3\u03bf\u03cd \u03c3\u03c5\u03bd\u03bf\u03bb\u03b9\u03ba\u03bf\u03cd \u03cd\u03c8\u03bf\u03c5\u03c2 362 \u03b5\u03ba\u03b1\u03c4. \u03b5\u03c5\u03c1\u03ce \u03c3\u03b5 \u03b5\u03c0\u03b9\u03c0\u03bb\u03ad\u03bf\u03bd 25.323 \u03b4\u03b9\u03ba\u03b1\u03b9\u03bf\u03cd\u03c7\u03bf\u03c5\u03c2 - Taxheaven.gr", "url": "https://www.taxheaven.gr/news/51957/epistreptea-prokatabolh-4-pistwsh-posoy-synolikoy-ypsoys-362-ekat-eyrw-se-epipleon-25323-dikaioyxoys", "author": "Taxheaven Newsroom", "publishedAt": "2020-12-10T16:09:44Z", "content": "\u00a9 Taxheaven - H - 5-710563 .: 2103332644e-mail: [email\u00a0protected]\r\n, 10 2020\r\n25.323 4 , 362 . .\r\n, 444.170, 2,16 . , .\r\n4 , , .\r\n, , , 5,5 . , , , .\r\nWebinar : 14-12-2020 17:30 : , \r\nWant to see com\u2026 [+156 chars]", "source": {"id": null, "name": "Taxheaven.gr"}, "urlToImage": "https://www.taxheaven.gr/uploads/images/taxheaven/covid151w.jpg"}, {"description": "\u039f\u03bb\u03bf\u03ba\u03bb\u03b7\u03c1\u03ce\u03b8\u03b7\u03ba\u03b5 \u03c4\u03bf \u03b1\u03c0\u03cc\u03b3\u03b5\u03c5\u03bc\u03b1 \u03c4\u03b7\u03c2 \u03a0\u03ad\u03bc\u03c0\u03c4\u03b7\u03c2 \u03b7 \u03c4\u03b7\u03bb\u03b5\u03b4\u03b9\u03ac\u03c3\u03ba\u03b5\u03c8\u03b7 \u03c4\u03b7\u03c2 \u03b5\u03c0\u03b9\u03c4\u03c1\u03bf\u03c0\u03ae\u03c2 \u03b5\u03bc\u03c0\u03b5\u03b9\u03c1\u03bf\u03b3\u03bd\u03c9\u03bc\u03cc\u03bd\u03c9\u03bd \u03c4\u03bf\u03c5 \u03c5\u03c0\u03bf\u03c5\u03c1\u03b3\u03b5\u03af\u03bf\u03c5 \u03a5\u03b3\u03b5\u03af\u03b1\u03c2, \u03b7 \u03bf\u03c0\u03bf\u03af\u03b1 \u03b5\u03af\u03c7\u03b5 \u03c9\u03c2 \u03b8\u03ad\u03bc\u03b1 \u03c4\u03bf \u03ac\u03bd\u03bf\u03b9\u03b3\u03bc\u03b1 \u03c4\u03bf\u03c5 \u03bb\u03b9\u03b1\u03bd\u03b5\u03bc\u03c0\u03bf\u03c1\u03af\u03bf\u03c5", "title": "\u039f\u03b9 \u03bb\u03bf\u03b9\u03bc\u03c9\u03be\u03b9\u03bf\u03bb\u03cc\u03b3\u03bf\u03b9 \u03b1\u03c0\u03bf\u03c6\u03ac\u03c3\u03b9\u03c3\u03b1\u03bd \u03ac\u03bd\u03bf\u03b9\u03b3\u03bc\u03b1 \u03ba\u03bf\u03bc\u03bc\u03c9\u03c4\u03b7\u03c1\u03af\u03c9\u03bd, \u03b2\u03b9\u03b2\u03bb\u03b9\u03bf\u03c0\u03c9\u03bb\u03b5\u03af\u03c9\u03bd \u03ba\u03b1\u03b9 click away \u03b3\u03b9\u03b1 \u03c4\u03b9\u03c2 \u03b3\u03b9\u03bf\u03c1\u03c4\u03ad\u03c2 - \u03a4\u03b1 \u039d\u03ad\u03b1 \u039fnline", "url": "https://www.tanea.gr/2020/12/10/greece/oi-loimoksiologoi-apofasisan-anoigma-kommotirion-vivliopoleion-kai-click-away-gia-tis-giortes/", "author": null, "publishedAt": "2020-12-10T15:40:29Z", "content": "Lockdown\r\n , \r\n \u00a0 , \u00a0.\r\n, , lockdown 7 . \r\n, \u00a0 , .\r\n, , , click away.\r\n: , \r\n ,\u00a0 \u00a0 , ,\u00a0 .\r\n, . , \u00ab \u00a0 . \u00a0 \u00bb.\r\n, Alpha, , , .\r\n, .\r\n.\u00a0\u00a0 \u00a0 \u00ab 100,3\u00bb, . , , .\r\n: \r\n , \u00a0 .\r\n\u00ab , - . ... . . .\r\n, .\r\n. \u00a0 , , \u2026 [+62 chars]", "source": {"id": null, "name": "Tanea.gr"}, "urlToImage": "https://www.tanea.gr/wp-content/uploads/2020/12/21_025_tk_1721-2_sooc1607439563.jpg"}, {"description": "\u039a\u03c5\u03c1\u03b9\u03ac\u03c1\u03c7\u03b7\u03c3\u03b1\u03bd \u03bf\u03b9 \u03c0\u03c9\u03bb\u03b7\u03c4\u03ad\u03c2 \u03bc\u03b5\u03c4\u03ac \u03b1\u03c0\u03cc 14 \u03c3\u03c5\u03bd\u03b5\u03c7\u03b5\u03af\u03c2 \u03b1\u03bd\u03bf\u03b4\u03b9\u03ba\u03ad\u03c2 \u03c3\u03c5\u03bd\u03b5\u03b4\u03c1\u03b9\u03ac\u03c3\u03b5\u03b9\u03c2 \u03c0\u03bf\u03c5 \u03c0\u03c1\u03bf\u03c3\u03ad\u03b8\u03b5\u03c3\u03b1\u03bd \u03ba\u03b5\u03c6\u03b1\u03bb\u03b1\u03b9\u03bf\u03c0\u03bf\u03af\u03b7\u03c3\u03b7 4,3 \u03b4\u03b9\u03c2. \u03b5\u03c5\u03c1\u03ce. \u03a3\u03c4\u03bf\u03bd \u03c4\u03c1\u03b1\u03c0\u03b5\u03b6\u03b9\u03ba\u03cc \u03ba\u03bb\u03ac\u03b4\u03bf \u03bf\u03b9 \u03c0\u03b5\u03c1\u03b9\u03c3\u03c3\u03cc\u03c4\u03b5\u03c1\u03b5\u03c2 \u03c1\u03b5\u03c5\u03c3\u03c4\u03bf\u03c0\u03bf\u03b9\u03ae\u03c3\u03b5\u03b9\u03c2, \u00ab\u03b1\u03bd\u03c4\u03af\u03c3\u03c4\u03b1\u03c3\u03b7\u00bb \u03b1\u03c0\u03cc Coca Cola, \u039c\u03c5\u03c4\u03b9\u03bb\u03b7\u03bd\u03b1\u03af\u03bf \u03ba\u03b1\u03b9 \u039f\u03a0\u0391\u03a0.", "title": "\u03a7\u03c1\u03b7\u03bc\u03b1\u03c4\u03b9\u03c3\u03c4\u03ae\u03c1\u03b9\u03bf: \u03a4\u03b1 \u03bc\u03b1\u03b8\u03ae\u03bc\u03b1\u03c4\u03b1 \u03b1\u03c0\u03cc \u03c4\u03b7\u03bd \u03c0\u03c1\u03ce\u03c4\u03b7 \u03b4\u03b9\u03cc\u03c1\u03b8\u03c9\u03c3\u03b7 - Euro2day", "url": "https://www.euro2day.gr/ase/market_comment/article-market/2055800/hrhmatisthrio-ta-mathhmata-apo-thn-proth-diorthosh.html", "author": null, "publishedAt": "2020-12-10T15:34:00Z", "content": ", , Brexit, .\r\n , . , 31 , .\r\n , .\r\n , 500 . (PEPP) . PEPP 2022 , ( , , ).\r\n . , , , , .\r\nFED 15 16 .\r\n , 14 , 13,85%, 10 , 14 , 4,3 ., , , , .\r\n 15 , .. 15 , .\r\n , , , Bull , .\r\n , .. , , FTSE25 , ,\u2026 [+1758 chars]", "source": {"id": null, "name": "Euro2day.gr"}, "urlToImage": "https://air.euro2day.gr/media/resizedpics/picsMain930/74/1475174-markets-down-6-930.jpg"}], "totalResults": 30}